{
  "tenant_id": "tenant_001",
  "export_id": "exp-001",
  "exported_at_utc": "2026-01-01T00:00:00.000Z",
  "events": [
    {
      "tenant_id": "tenant_001",
      "sequence": 1,
      "event": "CREATE",
      "entity": "invoice",
      "id": "INV-TAMPERED"
    },
    {
      "tenant_id": "tenant_001",
      "sequence": 2,
      "event": "UPDATE",
      "entity": "invoice",
      "id": "INV-001"
    }
  ],
  "bundle_checksum": "2331f154f44fbb5097c47bd75e7a51f3963eeac1a9026b5fcc0864449f154eeb"
}
